Metadata-Version: 2.1
Name: aldryn-bootstrap3-resurrected
Version: 1.3.84
Summary: Adds Bootstrap 3 components as plugins.
Home-page: https://github.com/avryhof/aldryn-bootstrap3
Author: Divio AG / Updated by Amos Vryhof
Author-email: amos@vryhofresearch.com
License: BSD
Classifier: Development Status :: 5 - Production/Stable
Classifier: Environment :: Web Environment
Classifier: Framework :: Django
Classifier: Intended Audience :: Developers
Classifier: License :: OSI Approved :: BSD License
Classifier: Operating System :: OS Independent
Classifier: Programming Language :: Python
Classifier: Programming Language :: Python :: 3
Classifier: Programming Language :: Python :: 3.7
Classifier: Programming Language :: Python :: 3.8
Classifier: Topic :: Internet :: WWW/HTTP
Classifier: Topic :: Internet :: WWW/HTTP :: Dynamic Content
Classifier: Topic :: Software Development :: Libraries :: Application Frameworks
Classifier: Topic :: Software Development :: Libraries :: Python Modules
License-File: LICENSE.txt
Requires-Dist: django >2.2
Requires-Dist: django-appconf >=1.0.0
Requires-Dist: django-cms >=3.5.0
Requires-Dist: django-filer >=0.9.11
Requires-Dist: djangocms-text-ckeditor >=3.1.0
Requires-Dist: djangocms-attributes-field >=0.1.1
